azskpy/__init__.py
azskpy/constants.py
azskpy/kubernetescontrols.py
azskpy/loganalytics.py
azskpy/main.py
azskpy/sparkcontrols.py
azskpy/utils.py
azskpy-0.9.65.dist-info/LICENSE.txt
azskpy-0.9.65.dist-info/METADATA
azskpy-0.9.65.dist-info/WHEEL
azskpy-0.9.65.dist-info/top_level.txt
azskpy-0.9.65.dist-info/RECORD
