Metadata-Version: 2.1
Name: azskpy
Version: 0.9.65
Summary: Scans Azure Controls
Home-page: https://aka.ms/azskpy
Author: AzSK Dev Team
Author-email: dsreazsksup@microsoft.com
License: UNKNOWN
Platform: UNKNOWN
Requires-Dist: kubernetes
Requires-Dist: applicationinsights
